{"OutputFileHashSum":"11AC0FF60E8105C27741D13B6BB1CC91C04D63EBB96FCCC2DF5CDD10A6C07B5D","Converted":true,"OutputModifyDate":"2018-09-21T11:08:34.6536187Z","Metadatas":[],"MetadataTypes":[{"CategoryName":"VuGen.Replay","MetadataTypeName":"HP.LR.Vugen.Iteration","Id":1},{"CategoryName":"VuGen.Replay","MetadataTypeName":"HP.LR.Vugen.NotifyTransaction","Id":2},{"CategoryName":"VuGen.Replay","MetadataTypeName":"Utt.Debugger.Error","Id":3},{"CategoryName":"VuGen.Replay","MetadataTypeName":"HP.LR.Vugen.NotifyAny","Id":4}]}